MANIFEST.in
setup.cfg
setup.py
test.py
scripts/xsdinspect
testcases/amendment-request-v102.xsd
xml_orm/__init__.py
xml_orm/common.py
xml_orm/core.py
xml_orm/errors.py
xml_orm/fields.py
xml_orm/inspect.py
xml_orm/util.py
xml_orm.egg-info/PKG-INFO
xml_orm.egg-info/SOURCES.txt
xml_orm.egg-info/dependency_links.txt
xml_orm.egg-info/entry_points.txt
xml_orm.egg-info/not-zip-safe
xml_orm.egg-info/top_level.txt