Metadata-Version: 1.0
Name: xml-orm
Version: 0.6.13
Summary: Yet another XML to python object mapping, a la Django ORM
Home-page: UNKNOWN
Author: Andrew Rodionoff
Author-email: andviro@gmail.com
License: LGPL
Platform: UNKNOWN
